tomlscript/__init__.py
tomlscript/main.py
tomlscript/parser.py
tomlscript/py.typed
tomlscript/utils.py
tomlscript-0.2.1.dist-info/METADATA
tomlscript-0.2.1.dist-info/WHEEL
tomlscript-0.2.1.dist-info/entry_points.txt
tomlscript-0.2.1.dist-info/licenses/LICENSE
tomlscript-0.2.1.dist-info/RECORD
