Metadata-Version: 2.3
Name: tomlscript
Version: 0.2.1
Summary: A lightweight, dependency-free tool to manage your scripts directly from pyproject.toml
Project-URL: Source, https://github.com/phihung/tomlscript
License-File: LICENSE
Requires-Python: >=3.10
Requires-Dist: tomli>=1; python_version < '3.11'
